LICENSE.txt
README.md
setup.py
example_python_package/__init__.py
example_python_package/foo_bar.py
example_python_package_ulturgashev.egg-info/PKG-INFO
example_python_package_ulturgashev.egg-info/SOURCES.txt
example_python_package_ulturgashev.egg-info/dependency_links.txt
example_python_package_ulturgashev.egg-info/top_level.txt
tests/__init__.py
tests/test_foo_bar.py