Metadata-Version: 2.1
Name: example_python_package_ulturgashev
Version: 0.0.1
Summary: Example python package
Home-page: https://github.com/ulturgashev/example_python_package
Author: ulturgashev
Author-email: ulturgashevvv@gmail.com
License-File: LICENSE.txt
